{
  "name": "BeamBook Dev Container",
  "dockerFile": "Dockerfile",
  "customizations": {
    "vscode": {
      "extensions": [
        "asciidoctor.asciidoctor-vscode",
        "github.copilot",
        "github.copilot-chat",
        "ms-azuretools.vscode-docker",
        "ms-python.debugpy",
        "ms-python.python",
        "ms-python.vscode-pylance",
        "ms-vscode.cmake-tools",
        "ms-vscode.cpptools",
        "ms-vscode.cpptools-extension-pack",
        "ms-vscode.cpptools-themes",
        "ms-vscode.makefile-tools",
        "erlang-language-platform.erlang-language-platform",
        "twxs.cmake",
        "editorconfig.editorconfig",
        "Shopify.ruby-lsp"
      ]
    },
    "settings": {
      "terminal.integrated.shell.linux": "/bin/bash"
    }
  }
}